mydir/__init__.py
mydir/__main__.py
mydir/_core.py
mydir-1.0.3.dist-info/licenses/LICENSE
mydir-1.0.3.dist-info/METADATA
mydir-1.0.3.dist-info/WHEEL
mydir-1.0.3.dist-info/entry_points.txt
mydir-1.0.3.dist-info/top_level.txt
mydir-1.0.3.dist-info/RECORD
