Metadata-Version: 2.4
Name: mydir
Version: 1.0.3
Summary: Directory tree visualiser & syntax‑highlighted code bundler (PDF/DOCX)
Author-email: Abdullah Al-Labani <abdtaha982@gmail.com>
License: MIT
Classifier: License :: OSI Approved :: MIT License
Classifier: Programming Language :: Python :: 3
Classifier: Programming Language :: Python :: 3 :: Only
Classifier: Topic :: Utilities
Requires-Python: >=3.9
License-File: LICENSE
Requires-Dist: Pygments>=2.17
Provides-Extra: pdf
Requires-Dist: weasyprint>=61; extra == "pdf"
Provides-Extra: doc
Requires-Dist: python-docx>=1.1; extra == "doc"
Dynamic: license-file
